data_pos/__init__.py
data_pos/data_R0.py
data_pos/data_pos.py
decomp/__init__.py
decomp/bz.py
decomp/cell.py
decomp/complete_spectrum.py
decomp/decomposition.py
decomp/olds.py
decomp/plot.py
decomp/post-proc.py
decomp/post_proc.py
decomp/read.py
decomp/util.py
phonon_dos-0.2.33.data/scripts/compl-spec
phonon_dos-0.2.33.data/scripts/data-R0
phonon_dos-0.2.33.data/scripts/data-pos
phonon_dos-0.2.33.data/scripts/pho-dos
phonon_dos-0.2.33.data/scripts/post-proc
phonon_dos-0.2.33.dist-info/DESCRIPTION.rst
phonon_dos-0.2.33.dist-info/METADATA
phonon_dos-0.2.33.dist-info/RECORD
phonon_dos-0.2.33.dist-info/WHEEL
phonon_dos-0.2.33.dist-info/metadata.json
phonon_dos-0.2.33.dist-info/top_level.txt
