Metadata-Version: 2.0
Name: phonon-dos
Version: 0.2.33
Summary: Phonon DOS
Home-page: https://gitlab.com/Coiana/phonon_dos
Author: Gabriele Coiana
Author-email: gabriele.coiana17@imperial.ac.uk
License: UNKNOWN
Platform: UNKNOWN
Classifier: Programming Language :: Python :: 3
Classifier: License :: OSI Approved :: MIT License
Classifier: Operating System :: OS Independent
